hyperlink_preview/__init__.py
hyperlink_preview/demo_html.py
hyperlink_preview/hyperlink_preview.py
hyperlink_preview/image_size.py
hyperlink_preview/utils.py
hyperlink_preview-1.0.4.dist-info/LICENSE
hyperlink_preview-1.0.4.dist-info/METADATA
hyperlink_preview-1.0.4.dist-info/WHEEL
hyperlink_preview-1.0.4.dist-info/top_level.txt
hyperlink_preview-1.0.4.dist-info/RECORD
