Metadata-Version: 2.1
Name: hyperlink-preview
Version: 1.0.4
Summary: Small visual preview and brief description of a http link: this library gets the data.
Home-page: https://github.com/gri38/hyperlink_preview
Author: gri38
Author-email: onzewb@zaclys.net
License: UNKNOWN
Project-URL: Bug Tracker, https://github.com/gri38/hyperlink_preview/issues
Platform: UNKNOWN
Classifier: Programming Language :: Python :: 3
Classifier: License :: OSI Approved :: MIT License
Classifier: Operating System :: OS Independent
Requires-Python: >=3.6
License-File: LICENSE
Requires-Dist: beautifulsoup4 (>=4.9.3)
Requires-Dist: requests (>=2.27.1)
